notional/__init__.py
notional/__main__.py
notional/blocks.py
notional/core.py
notional/iterator.py
notional/orm.py
notional/parser.py
notional/query.py
notional/schema.py
notional/session.py
notional/text.py
notional/types.py
notional/user.py
notional/util.py
notional/version.py
notional-0.8.1.dist-info/LICENSE
notional-0.8.1.dist-info/METADATA
notional-0.8.1.dist-info/WHEEL
notional-0.8.1.dist-info/RECORD
