Metadata-Version: 2.1
Name: notional
Version: 0.8.1
Summary: A high-level interface for the Notion SDK.
Home-page: https://github.com/jheddings/notional/
License: MIT
Author: Jason Heddings
Author-email: jheddings@gmail.com
Requires-Python: >=3.8.1,<4.0.0
Classifier: License :: OSI Approved :: MIT License
Classifier: Operating System :: OS Independent
Classifier: Programming Language :: Python :: 3
Classifier: Programming Language :: Python :: 3.9
Classifier: Programming Language :: Python :: 3.10
Classifier: Programming Language :: Python :: 3.11
Classifier: Programming Language :: Python :: 3.12
Classifier: Topic :: Software Development :: Libraries :: Python Modules
Requires-Dist: emoji (>=2.11.0,<3.0.0)
Requires-Dist: html5lib (>=1.1,<2.0)
Requires-Dist: notion-client (>=2.2.1,<3.0.0)
Requires-Dist: pydantic (>=1.10.15,<2.0.0)
Requires-Dist: urllib3 (>=1.26.18,<2.0.0)
Project-URL: Documentation, https://jheddings.github.io/notional/
Project-URL: Repository, https://github.com/jheddings/notional/
